LICENSE
tests_github_actions/__init__.py
tests_github_actions-0.1.1.dist-info/LICENSE
tests_github_actions-0.1.1.dist-info/WHEEL
tests_github_actions-0.1.1.dist-info/METADATA
tests_github_actions-0.1.1.dist-info/RECORD
