Metadata-Version: 2.1
Name: tests-github-actions
Version: 0.1.1
Summary: Package only tests Github Actions
Home-page: https://github.com/williamcanin/tests-github-actions
License: MIT
Keywords: tests,github,actions
Author: William C. Canin
Author-email: william.costa.canin@gmail.com
Requires-Python: >=3.9,<4.0
Classifier: License :: OSI Approved :: MIT License
Classifier: Programming Language :: Python :: 3
Classifier: Programming Language :: Python :: 3.9
Project-URL: Repository, https://github.com/williamcanin/tests-github-actions
